cmsplugin_googleplus/__init__.py
cmsplugin_googleplus/cms_plugins.py
cmsplugin_googleplus/conf.py
cmsplugin_googleplus/globals.py
cmsplugin_googleplus/googleplus.py
cmsplugin_googleplus/models.py
cmsplugin_googleplus/locale/en/LC_MESSAGES/django.mo
cmsplugin_googleplus/locale/en/LC_MESSAGES/django.po
cmsplugin_googleplus/locale/it/LC_MESSAGES/django.mo
cmsplugin_googleplus/locale/it/LC_MESSAGES/django.po
cmsplugin_googleplus/locale/pl/LC_MESSAGES/django.mo
cmsplugin_googleplus/locale/pl/LC_MESSAGES/django.po
cmsplugin_googleplus/migrations/0001_initial.py
cmsplugin_googleplus/migrations/0002_add_google_api_key.py
cmsplugin_googleplus/migrations/0003_alter_cmsplugin_ptr.py
cmsplugin_googleplus/migrations/__init__.py
cmsplugin_googleplus/templates/cmsplugin_googleplus/twitter_bootstrap.html
cmsplugin_googleplus/tests/__init__.py
cmsplugin_googleplus/tests/base.py
cmsplugin_googleplus/tests/test_cms_plugins.py
cmsplugin_googleplus/tests/test_googleplus.py
cmsplugin_googleplus/tests/test_models.py
cmsplugin_googleplus/tests/data/activities.json
cmsplugin_googleplus/tests/example_project/__init__.py
cmsplugin_googleplus/tests/example_project/urls.py
cmsplugin_googleplus-0.7.0.dist-info/DESCRIPTION.rst
cmsplugin_googleplus-0.7.0.dist-info/METADATA
cmsplugin_googleplus-0.7.0.dist-info/RECORD
cmsplugin_googleplus-0.7.0.dist-info/WHEEL
cmsplugin_googleplus-0.7.0.dist-info/metadata.json
cmsplugin_googleplus-0.7.0.dist-info/top_level.txt
