Metadata-Version: 2.0
Name: cmsplugin-googleplus
Version: 0.7.0
Summary: Django-CMS plugin for Google Plus Activities
Home-page: https://github.com/itbabu/cmsplugin-googleplus
Author: Marco Badan
Author-email: info@marcobadan.com
License: MIT License
Platform: UNKNOWN
Classifier: Development Status :: 4 - Beta
Classifier: Environment :: Web Environment
Classifier: Framework :: Django
Classifier: Intended Audience :: Developers
Classifier: License :: OSI Approved :: MIT License
Classifier: Operating System :: OS Independent
Classifier: Programming Language :: Python
Classifier: Programming Language :: Python :: 2.7
Classifier: Programming Language :: Python :: 3.3
Classifier: Programming Language :: Python :: 3.4
Classifier: Programming Language :: Python :: 3.5
Classifier: Topic :: Internet :: WWW/HTTP
Classifier: Topic :: Internet :: WWW/HTTP :: Dynamic Content
Requires-Dist: google-api-python-client (>=1.6.2)
Requires-Dist: python-dateutil (>=2.6.0)
